<?xml version="1.0" encoding="utf-8"?>
<extension version="3.0" type="plugin" group="system" method="upgrade">
	<name>PLG_SYSTEM_JNSPREDIRECT_NAME</name>
	<author>miniOrange Security Software Pvt. Ltd.</author>
	<authorEmail>info@xecurify.com</authorEmail>
	<authorUrl>www.miniorange.com</authorUrl>
	<creationDate>October 2019</creationDate>
	<copyright>Copyright 2015 miniOrange. All Rights Reserved.</copyright>
	<license>GNU General Public License version 3</license>
	<version>3.4</version>
	<description>PLG_SYSTEM_JNSPREDIRECT_XML_DESCRIPTION</description>
	<files>
		<filename plugin="jnspredirect">jnspredirect.php</filename>
	</files>
	<scriptfile>my_script.php</scriptfile>
	<languages>
		<language tag="en-GB">language/en-GB/en-GB.plg_system_jnspredirect.ini</language>
		<language tag="en-GB">language/en-GB/en-GB.plg_system_jnspredirect.sys.ini</language>
	</languages>
</extension>